ecgtools/__init__.py
ecgtools/builder.py
ecgtools/parsers/__init__.py
ecgtools/parsers/cesm.py
ecgtools/parsers/cmip.py
ecgtools/parsers/observations.py
ecgtools/parsers/utilities.py
ecgtools-2024.7.31.dist-info/LICENSE
ecgtools-2024.7.31.dist-info/METADATA
ecgtools-2024.7.31.dist-info/WHEEL
ecgtools-2024.7.31.dist-info/top_level.txt
ecgtools-2024.7.31.dist-info/RECORD
