Metadata-Version: 2.1
Name: ecgtools
Version: 2024.7.31
Summary: ESM Catalog Generation Utilities
Home-page: https://github.com/ncar-xdev/ecgtools
Maintainer: NCAR XDev Team
Maintainer-email: xdev@ucar.edu
License: Apache Software License 2.0
Project-URL: Documentation, https://ecgtools.readthedocs.io/
Project-URL: Source, https://github.com/ncar-xdev/ecgtools
Project-URL: Tracker, https://github.com/ncar-xdev/ecgtools/issues
Keywords: ecgtools
Classifier: Development Status :: 2 - Pre-Alpha
Classifier: License :: OSI Approved :: Apache Software License
Classifier: Natural Language :: English
Classifier: Programming Language :: Python :: 3
Classifier: Programming Language :: Python :: 3.8
Classifier: Programming Language :: Python :: 3.9
Classifier: Programming Language :: Python :: 3.10
Classifier: Topic :: Scientific/Engineering
Classifier: Operating System :: OS Independent
Classifier: Intended Audience :: Science/Research
Requires-Python: >=3.8
License-File: LICENSE
Requires-Dist: cf_xarray
Requires-Dist: joblib
Requires-Dist: netCDF4
Requires-Dist: xarray
Requires-Dist: pyyaml
Requires-Dist: pydantic>=2.0
Requires-Dist: pandas
Requires-Dist: fsspec
Requires-Dist: intake-esm>=2023.7.7
